odoo/addons/purchase_operating_unit/README.rst
odoo/addons/purchase_operating_unit/__init__.py
odoo/addons/purchase_operating_unit/__manifest__.py
odoo/addons/purchase_operating_unit/demo/purchase_order_demo.xml
odoo/addons/purchase_operating_unit/i18n/pt.po
odoo/addons/purchase_operating_unit/i18n/purchase_operating_unit.pot
odoo/addons/purchase_operating_unit/models/__init__.py
odoo/addons/purchase_operating_unit/models/account_invoice.py
odoo/addons/purchase_operating_unit/models/purchase_order.py
odoo/addons/purchase_operating_unit/readme/CONTRIBUTORS.rst
odoo/addons/purchase_operating_unit/readme/DESCRIPTION.rst
odoo/addons/purchase_operating_unit/readme/ROADMAP.rst
odoo/addons/purchase_operating_unit/readme/USAGE.rst
odoo/addons/purchase_operating_unit/report/__init__.py
odoo/addons/purchase_operating_unit/report/purchase_report.py
odoo/addons/purchase_operating_unit/security/purchase_security.xml
odoo/addons/purchase_operating_unit/static/description/icon.png
odoo/addons/purchase_operating_unit/static/description/index.html
odoo/addons/purchase_operating_unit/tests/__init__.py
odoo/addons/purchase_operating_unit/tests/test_po_security.py
odoo/addons/purchase_operating_unit/tests/test_purchase_operating_unit.py
odoo/addons/purchase_operating_unit/views/purchase_order_line_view.xml
odoo/addons/purchase_operating_unit/views/purchase_order_view.xml
odoo12_addon_purchase_operating_unit-12.0.1.1.0.dist-info/METADATA
odoo12_addon_purchase_operating_unit-12.0.1.1.0.dist-info/WHEEL
odoo12_addon_purchase_operating_unit-12.0.1.1.0.dist-info/top_level.txt
odoo12_addon_purchase_operating_unit-12.0.1.1.0.dist-info/RECORD
